streply/__init__.py
streply/capture.py
streply/debug.py
streply/request.py
streply/response.py
streply/scope.py
streply/session.py
streply/source.py
streply/streply.py
streply/trace.py
streply/utils.py
streply/entity/__init__.py
streply/entity/entity.py
streply/enum/__init__.py
streply/enum/flags.py
streply/enum/level.py
streply/handler/__init__.py
streply/handler/log_handler.py
streply/input/__init__.py
streply/input/dsn.py
streply/input/options.py
streply_sdk-0.0.3.dist-info/METADATA
streply_sdk-0.0.3.dist-info/WHEEL
streply_sdk-0.0.3.dist-info/top_level.txt
streply_sdk-0.0.3.dist-info/RECORD
