Metadata-Version: 2.1
Name: streply-sdk
Version: 0.0.3
Summary: The all-in-one monitoring app for smart devs (https://streply.com)
Author: Streply
Author-email: support@streply.com
Project-URL: Documentation, https://docs.streply.com/
Project-URL: Changelog, https://streply.com/changelog
Project-URL: Help & Support, https://streply.com/help
Classifier: Environment :: Web Environment
Classifier: License :: OSI Approved :: BSD License
Classifier: Operating System :: OS Independent
Classifier: Programming Language :: Python :: 3
Classifier: Programming Language :: Python :: 3.4
Classifier: Programming Language :: Python :: 3.5
Classifier: Programming Language :: Python :: 3.6
Classifier: Programming Language :: Python :: 3.7
Classifier: Programming Language :: Python :: 3.8
Classifier: Programming Language :: Python :: 3.9
Classifier: Programming Language :: Python :: 3.10
Classifier: Programming Language :: Python :: 3.11
Classifier: Programming Language :: Python :: 3.12
Classifier: Topic :: Software Development :: Libraries :: Python Modules
Requires-Python: >=3
